exql/__init__.py
exql/dao.py
exql/exql.py
exql/logger.py
exql/sql.py
exql-1.0.dist-info/LICENSE
exql-1.0.dist-info/METADATA
exql-1.0.dist-info/WHEEL
exql-1.0.dist-info/top_level.txt
exql-1.0.dist-info/RECORD
