Metadata-Version: 2.1
Name: exql
Version: 1.0
Summary: Persist Excel/CSV sheets to MySQL (and vice versa)
Home-page: https://github.com/taabishm2/exql
Author: Tabish
Author-email: taabishm2@gmail.com
License: UNKNOWN
Project-URL: Bug Tracker, https://github.com/taabishm2/exql/issues
Platform: UNKNOWN
Classifier: Programming Language :: Python :: 3
Classifier: License :: OSI Approved :: MIT License
Classifier: Operating System :: OS Independent
Requires-Python: >=3.6
